pytest_mark_ac/__init__.py
pytest_mark_ac/py.typed
pytest_mark_ac-1.1.2.dist-info/METADATA
pytest_mark_ac-1.1.2.dist-info/WHEEL
pytest_mark_ac-1.1.2.dist-info/entry_points.txt
pytest_mark_ac-1.1.2.dist-info/licenses/LICENSE
pytest_mark_ac-1.1.2.dist-info/RECORD
