Metadata-Version: 2.4
Name: pytest-mark-ac
Version: 1.1.2
Summary: Provides a marker to reference acceptance criteria from PyTest tests through annotations
Project-URL: Homepage, https://gitlab.com/Kencho1/pytest-mark-ac
Project-URL: Documentation, https://gitlab.com/Kencho1/pytest-mark-ac/-/blob/main/README.md
Project-URL: Repository, https://gitlab.com/Kencho1/pytest-mark-ac.git
Project-URL: Issues, https://gitlab.com/Kencho1/pytest-mark-ac/-/issues
Author: Jesús Alonso Abad
License-Expression: MIT
License-File: LICENSE
Classifier: Development Status :: 5 - Production/Stable
Classifier: Environment :: Plugins
Classifier: Framework :: Pytest
Classifier: Intended Audience :: Developers
Classifier: License :: OSI Approved :: MIT License
Classifier: Natural Language :: English
Classifier: Operating System :: OS Independent
Classifier: Programming Language :: Python :: 3
Classifier: Programming Language :: Python :: 3.11
Classifier: Programming Language :: Python :: 3.12
Classifier: Programming Language :: Python :: 3.13
Classifier: Programming Language :: Python :: 3.14
Classifier: Topic :: Software Development :: Libraries :: Python Modules
Classifier: Topic :: Software Development :: Testing
Requires-Python: >=3.11
Requires-Dist: pytest~=8.4
Provides-Extra: dev
Requires-Dist: mypy>=1.0; extra == 'dev'
Requires-Dist: pytest-cov>=4.0; extra == 'dev'
Requires-Dist: ruff>=0.8.0; extra == 'dev'
Requires-Dist: tox>=4.0; extra == 'dev'
Provides-Extra: test
Requires-Dist: pytest-cov>=4.0; extra == 'test'
Requires-Dist: pytest~=8.4; extra == 'test'
